PolygonCollision/__init__.py
PolygonCollision/shape.py
PolygonCollision/vector.py
PolygonCollision/velocity.py
PolygonCollision-0.0.6.dist-info/METADATA
PolygonCollision-0.0.6.dist-info/WHEEL
PolygonCollision-0.0.6.dist-info/top_level.txt
PolygonCollision-0.0.6.dist-info/RECORD
