Metadata-Version: 2.1
Name: PolygonCollision
Version: 0.0.6
Summary: A simple python collision dectection tool
Author: made-up
Project-URL: Homepage, https://github.com/vertmit/PolygonCollision
Project-URL: Bug Tracker, https://github.com/vertmit/PolygonCollision/issues
Classifier: Programming Language :: Python :: 3
Classifier: License :: OSI Approved :: MIT License
Classifier: Operating System :: OS Independent
Requires-Python: >=2.7
